[
    {
        "id": "1",
        "brand": "Femmto",
        "model": "CG001-Azul",
        "fullName": ["Femmto", "CG001-Azul"],
        "img": [
            "https://http2.mlstatic.com/D_NQ_NP_2X_607586-MLA50209395075_062022-F.webp",
            "https://http2.mlstatic.com/D_NQ_NP_2X_748520-MLA50415595917_062022-F.webp",
            "https://http2.mlstatic.com/D_NQ_NP_2X_842296-MLA48982704770_012022-F.webp"
        ],
        "color": [ "naranja, natural"],
        "price": 16355.99,
        "strings": 6,
        "description": "Disfrutá con esta guitarra Femmto de la conexión con la música. Está diseñada para aficionados y profesionales. Con este instrumento descubrirás nuevos acordes.",
        "stock": 5,
        "discount": "0%",
        "type": "Criolla",
        "Additional-information": "Hacemos envios a todo el pais"
    },
    {
        "id": "2",
        "brand": "Yamaha",
        "model": "C40",
        "fullName": ["Yamaha", "C40"],
        "img": [
            "https://http2.mlstatic.com/D_NQ_NP_2X_688069-MLA44114804079_112020-F.webp",
            "https://http2.mlstatic.com/D_NQ_NP_2X_844728-MLA44114807092_112020-F.webp"
        ],
        "color": ["negro, natural"],
        "price": 52321.30,
        "strings": 6,
        "description": "Acabado en laca brillante, clavijero tipo lira de perfecta afinación y suave funcionamiento, Está diseñada para aficionados y profesionales.",
        "stock": 5,
        "discount": "0%",
        "type": "Criolla",
        "left-hand": false,
        "Additional-information": "Hacemos envios a todo el pais"
    },
    {
        "id": "3",
        "brand": "Midiplus",
        "model": "Clásica con funda",
        "fullName": ["Midiplus", "Clásica con funda"],
        "img": [
            "https://http2.mlstatic.com/D_NQ_NP_2X_994179-MLA48378987512_112021-F.webp"
        ],
        "color": [
            "natural"
        ],
        "price": 12464.30,
        "strings": 6,
        "description": "Guitarra con la altura de cuerdas justa, ideal para aprender, recomendada por profesores.",
        "stock": 4,
        "discount": "0%",
        "type": "Criolla",
        "left-hand": true,
        "Additional-information": "Hacemos envios a todo el pais"
    },
    {
        "id": "4",
        "brand": "Valencia",
        "model": "VC104K",
        "fullName": ["Valencia", "VC104K"],
        "img": [
            "https://http2.mlstatic.com/D_NQ_NP_2X_911829-MLA44548355323_012021-F.webp",
            "https://http2.mlstatic.com/D_NQ_NP_2X_606025-MLA44548355345_012021-F.webp"
        ],
        "color": [
            "natural"
        ],
        "price": 28541.35,
        "strings": 6,
        "description": "La longitud de la escala del mástil le permite tocar con el estilo clásico; justo lo que necesita para desarrollar la técnica adecuada.",
        "stock": 4,
        "discount": "0%",
        "type": "Criolla",
        "left-hand": false,
        "Additional-information": "Hacemos envios a todo el pais"
    },
    {
        "id": "5",
        "brand": "Parquer",
        "model": "GC109",
        "fullName": ["Parquer", "GC109"],
        "img": [
            "https://http2.mlstatic.com/D_NQ_NP_2X_840527-MLA47886167183_102021-F.webp",
            "https://http2.mlstatic.com/D_NQ_NP_2X_968661-MLA45333535518_032021-F.webp"
        ],
        "color": [
            "negro"
        ],
        "price": 16529,
        "strings": 6,
        "description": "Al ser una guitarra semisólida, y a pesar de su escaso espesor (unos 5 cm.) posee gran resonancia y un sonido muy calido.",
        "stock": 6,
        "discount": "0%",
        "type": "Criolla",
        "left-hand": false,
        "Additional-information": "Hacemos envios a todo el pais"
    },
    {
        "id": "6",
        "brand": "La Alpujarra",
        "model": "70",
        "fullName": ["La Alpujarra", "70"],
        "img": [
            "https://http2.mlstatic.com/D_NQ_NP_2X_973288-MLA50785418604_072022-F.webp",
            "https://http2.mlstatic.com/D_NQ_NP_2X_827027-MLA50785418603_072022-F.webp",
            "https://http2.mlstatic.com/D_NQ_NP_2X_749202-MLA50785395674_072022-F.webp"
        ],
        "color": [
            "natural"
        ],
        "price": 53999.41,
        "strings": 6,
        "description": "Exelente guitarra para iniciar a tocar, El instrumento en su totalidad tiene una terminación muy cuidada, un mango muy cómodo y un satinado de primera",
        "stock": 3,
        "discount": "0%",
        "type": "Criolla",
        "left-hand": false,
        "Additional-information": "Hacemos envios a todo el pais"
    },
    {
        "id": "7",
        "brand": "Famusic",
        "model": "Clásica",
        "fullName": ["Famusic", "Clásica"],
        "img": [
            "https://http2.mlstatic.com/D_NQ_NP_2X_783640-MLA45683269322_042021-F.webp"
        ],
        "color": [
            "negro"
        ],
        "price": 10999,
        "strings": 6,
        "description": "Exelente guitarra para iniciar a tocar, Parquer entrega los mejores instrumentos a personas apasionadas de todo el mundo",
        "stock": 8,
        "discount": "0%",
        "type": "Criolla",
        "left-hand": false,
        "Additional-information": "Hacemos envios a todo el pais"
    },
    {
        "id": "8",
        "brand": "Parquer",
        "model": "GC109LBM",
        "fullName": ["Parquer", "GC109LBM"],
        "img": [
            "https://http2.mlstatic.com/D_NQ_NP_2X_811362-MLA47725448613_102021-F.webp",
            "https://http2.mlstatic.com/D_NQ_NP_2X_762043-MLA47725448615_102021-F.webp"
        ],
        "color": [
            "natural"
        ],
        "price": 13677,
        "strings": 6,
        "description": "Exelente guitarra para iniciar a tocar, Está diseñada para aficionados y profesionales.",
        "stock": 15,
        "discount": "0%",
        "type": "Criolla",
        "left-hand": false,
        "Additional-information": "Hacemos envios a todo el pais"
    },
    {
        "id": "9",
        "brand": "Parquer",
        "model": "GC830",
        "fullName": ["Parquer", "GC830"],
        "img": [
            "https://http2.mlstatic.com/D_NQ_NP_2X_659594-MLA49106206574_022022-F.webp",
            "https://http2.mlstatic.com/D_NQ_NP_2X_605632-MLA49106206565_022022-F.webp"
        ],
        "color": [
            "roja"
        ],
        "price": 19726.40,
        "strings": 6,
        "description": "Exelente guitarra para iniciar a tocar, Parquer entrega los mejores instrumentos a personas apasionadas de todo el mundo",
        "stock": 9,
        "discount": "10%",
        "type": "Criolla",
        "left-hand": true,
        "Additional-information": "Hacemos envios a todo el pais"
    },
    {
        "id": "10",
        "brand": "Parquer",
        "model": "GC830",
        "fullName": ["Parquer", "GC830"],
        "img": [
            "https://http2.mlstatic.com/D_NQ_NP_2X_627109-MLA45642269637_042021-F.webp"
        ],
        "color": [
            "azul"
        ],
        "price": 19726.30,
        "strings": 6,
        "description": "Exelente guitarra para iniciar a tocar, Disfrutá con esta guitarra Custom de la conexión con la música",
        "stock": 7,
        "discount": "0%",
        "type": "Criolla",
        "left-hand": false,
        "Additional-information": "Hacemos envios a todo el pais"
    },
    {
        "id": "11",
        "brand": "Parquer",
        "model": "Stratocaster",
        "fullName": ["Parquer", "Stratocaster"],
        "img": [
            "https://http2.mlstatic.com/D_NQ_NP_622407-MLA48680123789_122021-O.webp, https://http2.mlstatic.com/D_NQ_NP_723793-MLA48680228384_122021-O.webp"
        ],
        "color": [
            "negro, blanco"
        ],
        "price": 37338,
        "strings": 6,
        "description": "Disfrutá con esta guitarra Parquer Custom de la conexión con la música. Con este instrumento descubrirás nuevos acordes, entonarás tus canciones y disfrutarás de la vida musical.",
        "stock": 15,
        "discount": "0%",
        "type": "Electrica",
        "left-hand": false,
        "Additional-information": "Material versátil: su madera de caoba la hace un producto versátil y popular."
    },
    {
        "id": "12",
        "brand": "Dakota",
        "model": "Stratocaster",
        "fullName": ["Dakota", "Stratocaster"],
        "img": [
            "https://http2.mlstatic.com/D_NQ_NP_632217-MLA48786922827_012022-O.webp, https://http2.mlstatic.com/D_NQ_NP_729274-MLA51537199502_092022-O.webp"
        ],
        "color": [
            "negro, roja"
        ],
        "price": 49990,
        "strings": 6,
        "description": "Fabricada íntegramente en madera (aliso+ arce). Es un producto importado, de primera calidad y la más completa del mercado: incluye bolso con cierre y accesorios!",
        "stock": 8,
        "discount": "0%",
        "type": "Electrica",
        "left-hand": false,
        "Additional-information": "Marca: DAKOTA, Tipo: Stratocaster, Pastillas: 3 bobinas simples, Controles: 1 Volumen, 2 Tonos, Incluye: Funda para transporte, Cable para conectar, Palanca trémolo, Llaves Allen"
    },
    {
        "id": "13",
        "brand": "Epiphone",
        "model": "Les Paul",
        "fullName": ["Epiphone", "Les Paul"],
        "img": [
            "https://http2.mlstatic.com/D_NQ_NP_669840-MLA46353231579_062021-O.webp, https://http2.mlstatic.com/D_NQ_NP_888651-MLA46352606590_062021-O.webp"
        ],
        "color": [
            "negro"   
        ],
        "price": 62074,
        "strings": 6,
        "description": "Esta Les Paul cuenta con pastillas, tono independiente y controles de volumen para cada elemento, lo que produce distintos resultados. El punto fuerte en su sonido es ser distorsionado, denso, contundente, potente y redondo.",
        "stock": 7,
        "discount": "0%",
        "type": "Electrica",
        "left-hand": true,
        "Additional-information": "Marca: DAKOTA, Tipo: Stratocaster, Pastillas: 3 bobinas simples, Controles: 1 Volumen, 2 Tonos, Incluye: Funda para transporte, Cable para conectar, Palanca trémolo, Llaves Allen"
    },
    {
        "id": "14",
        "brand": "Cort",
        "model": "X100",
        "fullName": ["Cort", "X100"],
        "img": [
            "https://http2.mlstatic.com/D_NQ_NP_625922-MLA48678794814_122021-O.webp, https://http2.mlstatic.com/D_NQ_NP_898081-MLA51375602262_092022-O.webp, https://http2.mlstatic.com/D_NQ_NP_779601-MLA51439631218_092022-O.webp"
        ],
        "color": [
            "negro, blanco"
        ],
        "price": 62674,
        "strings": 6,
        "description": "Cort entrega los mejores instrumentos a personas apasionadas de todo el mundo. Trabaja bajo cuidadosos estándares de selección y pulido de madera y cada uno de los elementos que componen sus guitarras",
        "stock": 10,
        "discount": "0%",
        "type": "Electrica",
        "left-hand": false,
        "Additional-information": "Selector de micrófonos: 3 posiciones, Cantidad de trastes: 24, Con palanca: Sí, Construcción del mástil: Bolt-on, Tipo de micrófono puente: Humbucker Powersound, Tipo de puente: Tremolo"
    },
    {
        "id": "15",
        "brand": "SX",
        "model": "Telecaster",
        "fullName": ["SX", "Telecaster"],
        "img": [
            "https://http2.mlstatic.com/D_NQ_NP_635048-MLA48123653039_112021-O.webp, https://http2.mlstatic.com/D_NQ_NP_903661-MLA48123721123_112021-O.webp"
        ],
        "color": [
            "azul, negro"
        ],
        "price": 62674,
        "strings": 6,
        "description": "Con esta Telecaster tocá las mejores canciones de country y rock. Cuenta con dos pastillas que tienen un diseño casi microfónico y le permiten captar con riqueza todos los matices y armónicos.",
        "stock": 16,
        "discount": "0%",
        "type": "Electrica",
        "left-hand": true,
        "Additional-information": "Selector de micrófonos: 3 posiciones, Cantidad de trastes: 21, Con palanca: Sí, Construcción del mástil: Bolt-on, Tipos de control: Selector de micrófonos, Tono, Volumen, Tipo de micrófono mástil: Single Coil"
    },
    {
        "id": "16",
        "brand": "Kramer",
        "model": "Vanguard",
        "fullName": ["Kramer", "Vanguard"],
        "img": [
            "https://http2.mlstatic.com/D_NQ_NP_994438-MLA31586492212_072019-O.webp"
        ],
        "color": [
            "negro"
        ],
        "price": 135815,
        "strings": 6,
        "description": "Puente de trémolo Floyd Rose empotrado. 2 humbuckers de Alnico V. Volumen sangrado mod. 1 vol. 1 tono con división de bobina push-pull. Interruptor de selección de 3 vías.",
        "stock": 5,
        "discount": "0%",
        "type": "Electrica",
        "left-hand": false,
        "Additional-information": "Hacemos envios a todo el pais"
    },
    {
        "id": "17",
        "brand": "PRS",
        "model": "SE Custom",
        "fullName": ["PRS", "SE Custom"],
        "img": [
            "https://http2.mlstatic.com/D_NQ_NP_783212-MLA48416164849_122021-O.webp, https://http2.mlstatic.com/D_NQ_NP_865065-MLA48416202595_122021-O.webp, https://http2.mlstatic.com/D_NQ_NP_823266-MLA48416279145_122021-O.webp"
        ],
        "color": [
            "negro"
        ],
        "price": 532627,
        "strings": 6,
        "description": " la guitarra icónica que comenzó todo en 1985. La Custom 24-08 mantiene todas las especificaciones fundamentales del instrumento, al tiempo que lleva la plataforma Custom a nuevos territorios sonoros.",
        "stock": 5,
        "discount": "0%",
        "type": "Electrica",
        "left-hand": false,
        "Additional-information": "Número de trastes: 24, Micrófono del mango: TCI “S”, Micrófono del puente: TCI “S”, Controles: volumen y tono con llave selectora de 3 vías y switch individuales para convertir los humbuckers en sigle coils"
    },
    {
        "id": "18",
        "brand": "Gretsch",
        "model": "Hollow G6136T",
        "fullName": ["Gretsch", "Hollow G6136T"],
        "img": [
            "https://http2.mlstatic.com/D_NQ_NP_936630-MLA44189744930_112020-O.webp"
        ],
        "color": [
            "blanco"
        ],
        "price": 292117,
        "strings": 6,
        "description": "Guitarra Eléctrica GRETSCH WHITE FALCON MODELO 6136T Con estuche y papelería, certificado de autenticidad",
        "stock": 5,
        "discount": "0%",
        "type": "Electrica",
        "left-hand": false,
        "Additional-information": "Hacemos envios a todo el pais"
    },
    {
        "id": "19",
        "brand": "Cort",
        "model": "Explorer Vx-2V",
        "fullName": ["Cort", "Explorer Vx-2V"],
        "img": [
            "https://http2.mlstatic.com/D_NQ_NP_664769-MLA48124486066_112021-O.webp"
        ],
        "color": [
            "negro"
        ],
        "price": 12673,
        "strings": 6,
        "description": "Las formas agresivas del cuerpo del VX se complementan con pastillas EMG-HZ y trémolo de bloqueo doble. El VX-2X tiene un mástil reforzado de 5 piezas para mayor resistencia y estabilidad.",
        "stock": 12,
        "discount": "0%",
        "type": "Electrica",
        "left-hand": false,
        "Additional-information": "Construcción: Atornillado, Cuerpo: Agathis, Diapasón: Palisandro, Radio de 12 pulgadas,  Puente: Tune-o-matic bridge (LP2) & stop tailpiece,  Pastillas: EMG-HZ SA1 (F) y TB1 (R) (HH)."
    },
    {
        "id": "20",
        "brand": "Ibanez",
        "model": "GSA60",
        "fullName": ["Ibanez", "GSA60"],
        "img": [
            "https://http2.mlstatic.com/D_NQ_NP_760628-MLA48678675895_122021-O.webp, https://http2.mlstatic.com/D_NQ_NP_740895-MLA48678701559_122021-O.webp, https://http2.mlstatic.com/D_NQ_NP_672009-MLA48678794445_122021-O.webp"
        ],
        "color": [
            "negro, azul"
        ],
        "price": 8970,
        "strings": 6,
        "description": "Si algo caracteriza a las guitarras de Ibanez es su estilo, con cuellos más delgados y diapasones más planos, electrónica de alta potencia y acabados coloridos. Esta marca es una de las más versátiles del mercado.",
        "stock": 5,
        "discount": "0%",
        "type": "Electrica",
        "left-hand": false,
        "Additional-information": "Con palanca: Sí, Cantidad de micrófonos: 3, Cantidad de trastes: 22, Tipo de micrófono mástil: Infinity RS (S), Tipo de micrófono puente: Infinity R (H), Tipos de micrófonos: Humbucker, Simple."
    },
    {
        "id": "21",
        "brand": "Gracia",
        "model": "M6",
        "fullName": ["Gracia", "M6"],
        "img": [
            "https://http2.mlstatic.com/D_NQ_NP_2X_950354-MLA50448314181_062022-F.webp",
            "https://http2.mlstatic.com/D_NQ_NP_2X_947252-MLA50448012948_062022-F.webp"
        ],
        "color": [
            "natural"
        ],
        "price": 30272,
        "strings": 6,
        "description": "Material del daipasón: nogal, Color: natural, Orientación de la mano: diestro, Tipo de guitarra: clásica, Material de la tapa: Saúco, Con corte: sí, Cantidad de cuerdas: 6, Materiales del fondo: -",
        "stock": 5,
        "discount": "0%",
        "type": "Criolla",
        "left-hand": false,
        "Additional-information": "Con un toque artesanal único plasmado en sus materiales, Gracia acompaña a la historia musical desde el año 1870. Sus guitarras poseen alcance internacional."
    },
    {
        "id": "22",
        "brand": "Gracia",
        "model": "Fa01",
        "fullName": ["Gracia", "Fa01"],
        "img": [
            "https://http2.mlstatic.com/D_NQ_NP_2X_999703-MLA48680702780_122021-F.webp"
        ],
        "color": [
            "natural"
        ],
        "price": 29638.75,
        "strings": 6,
        "description": "GUITARRA CLASICA CRIOLLA PARA ZURDOS GRACIA FA01, Tamaño: Normal, Modelo para zurdos, Caja: Abedul sin cenefas, Mástil: Cedro paraguayo, Diapasón: Nogal, Entrastadura: Bronce, Clavijero: Niquelado grabado, Color Natural Ó ESFUMADO",
        "stock": 6,
        "discount": "0%",
        "type": "Criolla",
        "left-hand": true,
        "Additional-information": "Todos los productos en Oferta, Outlet y/o SALE%, han estado en exhibición y poseen detalles estéticos que no afectan el normal funcionamiento, Packaging deteriorado y/o pueden NO tener la caja original."
    },
    {
        "id": "23",
        "brand": "Gracia",
        "model": "M10",
        "fullName": ["Gracia", "M10"],
        "img": [
            "https://http2.mlstatic.com/D_NQ_NP_2X_956901-MLA50496713038_062022-F.webp",
            "https://http2.mlstatic.com/D_NQ_NP_2X_926158-MLA50496713046_062022-F.webp",
            "https://http2.mlstatic.com/D_NQ_NP_2X_988643-MLA50496713042_062022-F.webp",
            "https://http2.mlstatic.com/D_NQ_NP_2X_971832-MLA50496713037_062022-F.webp"
        ],
        "color": [
            "natural"
        ],
        "price": 50348,
        "strings": 6,
        "description": "Guitarra Clásica Criolla C/Mic Gracia M10 EQ Afinador, Medio concierto, Caja con corte, madera de Nogal 4/4., Tapa de Pino importado, Mango de Cedro Paraguayo, Trastera de Nogal seleccionado, Entrastadura de Bronce.",
        "stock": 5,
        "discount": "0%",
        "type": "Criolla",
        "left-hand": false,
        "Additional-information": "Todos los productos en Oferta, Outlet y/o SALE%, han estado en exhibición y poseen detalles estéticos que no afectan el normal funcionamiento, Packaging deteriorado y/o pueden NO tener la caja original."
    },
    {
        "id": "24",
        "brand": "Gracia",
        "model": "345",
        "fullName": ["Gracia", "345"],
        "img": [
            "https://http2.mlstatic.com/D_NQ_NP_2X_816596-MLA43833896132_102020-F.webp",
            "https://http2.mlstatic.com/D_NQ_NP_2X_630241-MLA43823487497_102020-F.webp",
            "https://http2.mlstatic.com/D_NQ_NP_2X_979025-MLA43823357767_102020-F.webp",
            "https://http2.mlstatic.com/D_NQ_NP_2X_866008-MLA43823357837_102020-F.webp"
        ],
        "color": [
            "natural"
        ],
        "price": 76486.59,
        "strings": 6,
        "description": "Color: natural, Orientación de la mano: diestro, Tipo de guitarra: acústica, Material de la tapa: caoba, Materiales de fondo: caoba, Materiales de los laterales: caoba, Con corte: sí, Cantidad de cuerdas: -",
        "stock": 4,
        "discount": "0%",
        "type": "Criolla",
        "left-hand": false,
        "Additional-information": "Con un toque artesanal único plasmado en sus materiales, Gracia acompaña a la historia musical desde el año 1870. Sus guitarras poseen alcance internacional y son utilizadas tantos por principiantes como por grandes referentes de la música."
    },
    {
        "id": "25",
        "brand": "Gracia",
        "model": "Niño Infantil Rosa",
        "fullName": ["Gracia", "Niño Infantil Rosa"],
        "img": [
            "https://http2.mlstatic.com/D_NQ_NP_2X_734413-MLA41633975042_052020-F.webp",
            "https://http2.mlstatic.com/D_NQ_NP_2X_742521-MLA41633918797_052020-F.webp",
            "https://http2.mlstatic.com/D_NQ_NP_2X_912902-MLA41633970121_052020-F.webp"
        ],
        "color": [
            "rosa"
        ],
        "price": 22159.07,
        "strings": 6,
        "description": "Caracteristicas TAMAÑO: 1/2, CAJA: Abedul, BRAZO: Cedro Paraguayo, DIAPASON: Nogal, ENTRASTADURA: Bronce, CLAVIJERO: Niquelado grabado, MEDIDAS DE LA GUITARRA: Largo total 88,5 cm, Ancho de caja 30,5 cm, Largo de Caja 42 cm, Ancho de Diapasón 4,5 cm, Largo de Diapasón 36 cm, Largo de Puente 17 cm",
        "stock": 5,
        "discount": "0%",
        "type": "Criolla",
        "left-hand": false,
        "Additional-information": "Emitimos factura A y B. Si solicita factura A y su CUIT es de la provincia de Bs As puede tener un ajuste en el monto facturado con el concepto de percepción de IBB. Somos Agentes de retención y el porcentaje dependerá de su condición como contribuyente ante ARBA."
    },
    {
        "id": "26",
        "brand": "Fonseca",
        "model": "39Kec",
        "fullName": ["Fonseca", "39Kec"],
        "img": [
            "https://http2.mlstatic.com/D_NQ_NP_2X_923136-MLA47729678658_102021-F.webp"
        ],
        "color": [
            "negro"
        ],
        "price": 51021.25,
        "strings": 6,
        "description": "Fonseca Modelo 39Kec, Guitarra de estudio con Corte (Cutaway) y Ecualizador de 4 bandas más volumen y afinador. Características Tapa: Imitación Pino, Aros: Abedul Macizo, Fondo: Abedul Laminado, Corte: Si, Mástil: Cedro, Diapasón: Guayubira, Trastes: Alpaca, Clavijero: Niquelado Grabado, Lustre: Color Negro Brillante",
        "stock": 5,
        "discount": "0%",
        "type": "Criolla",
        "left-hand": false,
        "Additional-information": "*( El tono de la tapa o mastil puede variar en tono oscuro o claro dependiendo del fabricante )."
    },
    {
        "id": "27",
        "brand": "Fonseca",
        "model": "10",
        "fullName": ["Fonseca", "10"],
        "img": [
            "https://http2.mlstatic.com/D_NQ_NP_2X_971931-MLA31062642705_062019-F.webp",
            "https://http2.mlstatic.com/D_NQ_NP_2X_648890-MLA26266343332_102017-F.webp",
            "https://http2.mlstatic.com/D_NQ_NP_2X_633443-MLA31062638237_062019-F.webp"
        ],
        "color": [
            "natural"
        ],
        "price": 34757.26,
        "strings": 6,
        "description": "Guitarra criolla medio concierto tamaño mediano ideal para chicos de entre 6 y 12 años - industria argentina, guitarra criolla tamaño 3/4 -, fonseca, modelo:10, estudio superior para niños de 6 a 12 años",
        "stock": 2,
        "discount": "0%",
        "type": "Criolla",
        "left-hand": false,
        "Additional-information": "Cuando clickeas en “comprar” asumis el compromiso de compra. Por lo tanto te recomendamos que antes: 1. Estés seguro de querer adquirir el artículo., 2. Consultes el saldo disponible de tu tarjeta de crédito, 3."
    },
    {
        "id": "28",
        "brand": "Fonseca",
        "model": "25 de Estudio",
        "fullName": ["Fonseca", "25 de Estudio"],
        "img": [
            "https://http2.mlstatic.com/D_NQ_NP_2X_612080-MLA43168277679_082020-F.webp",
            "https://http2.mlstatic.com/D_NQ_NP_2X_746560-MLA43168277692_082020-F.webp",
            "https://http2.mlstatic.com/D_NQ_NP_2X_744199-MLA43168277690_082020-F.webp"
        ],
        "color": [
            
            "natural, negro"
        ],
        "price": 29912,
        "strings": 6,
        "description": "Guitarra Clasica Criolla Fonseca Modelo 25 De Estudio, Guitarra Criolla Clásica Fonseca, Modelo: 25 de Estudio, Tapa imitacion Pino, Aros y fondo de abedul, Mastil de Cedro, Diapason de nogal, Clavijero lira grabado, Color Natural o esfumado, disponibles según stock.",
        "stock": 3,
        "discount": "0%",
        "type": "Criolla",
        "left-hand": false,
        "Additional-information": "Todos los productos en Oferta, Outlet y/o SALE%, han estado en exhibición y poseen detalles estéticos que no afectan el normal funcionamiento, Packaging deteriorado y/o pueden NO tener la caja original."
    },
    {
        "id": "29",
        "brand": "Fonseca",
        "model": "31",
        "fullName": ["Fonseca", "31"],
        "img": [
            "https://http2.mlstatic.com/D_NQ_NP_2X_839515-MLA44373310655_122020-F.webp",
            "https://http2.mlstatic.com/D_NQ_NP_2X_945976-MLA47474505561_092021-F.webp",
            "https://http2.mlstatic.com/D_NQ_NP_2X_823696-MLA44373286445_122020-F.webp"
        ],
        "color": [
            "natural"
        ],
        "price": 39999,
        "strings": 6,
        "description": "GUITARRA CRIOLLA, Marca Fonseca, Modelo 31, Tapa de pino abeto laminado, Aros de nogal macizo, Fondo de nogal laminado, Ornamentos de doble filete negro, Mástil de cedro, Diapasón de nogal, Traste de bronce, Clavijero niquelado grabado, Lustre natural mate, Cuerdas de nylon.",
        "stock": 3,
        "discount": "0%",
        "type": "Criolla",
        "left-hand": false,
        "Additional-information": "Las IMÁGENES en la presente publicación usualmente son provistas por los proveedores por lo que son a modo ilustrativo y pueden ser modificadas por los fabricantes/importadores sin previo aviso."
    },
    {
        "id": "30",
        "brand": "Fonseca",
        "model": "65 Medio Concierto",
        "fullName": ["Fonseca", "65 Medio Concierto"],
        "img": [
            "https://http2.mlstatic.com/D_NQ_NP_2X_789523-MLA40735270399_022020-F.webp",
            "https://http2.mlstatic.com/D_NQ_NP_2X_939881-MLA40735266485_022020-F.webp"
        ],
        "color": [
            "natural"
        ],
        "price": 54944.04,
        "strings": 6,
        "description": "Guitarra Fonseca 65 Características: Tapa: Pino Abeto Laminado con Mosaicos, Aros: Algarrobo Macizo, Fondo: Algarrobo Laminado, Ornamentos: Doble Filete de Palo Blanco; Cenefa Central en el Fondo, Mástil: Cedro, Diapasón: Nogal, Trastes: Alpaca, Clavijero: Dorado Grabado, Lustre: Natural Brillante",
        "stock": 7,
        "discount": "0%",
        "type": "Criolla",
        "left-hand": false,
        "Additional-information": "Importante: Cuando clickeas en “comprar” asumis el compromiso de compra. Por lo tanto te recomendamos que antes: 1. Estés seguro de querer adquirir el artículo., 2. Consultes el saldo disponible de tu tarjeta de crédito, 3."
    }

    ,
    {
        "id": "31",
        "brand": "Newen",
        "model": "TL",
        "fullName": ["Fonseca", "65 Medio Concierto"],
        "img": [
            "https://http2.mlstatic.com/D_NQ_NP_850084-MLA51714111515_092022-O.webp",
            "https://http2.mlstatic.com/D_NQ_NP_704471-MLA51714111568_092022-O.webp"
        ],
        "color": [ "blanco, azul"],
        "price": 78944.04,
        "strings": 6,
        "description": "Disfrutá con esta guitarra Newen de la conexión con la música. Con este instrumento descubrirás nuevos acordes, entonarás tus canciones y disfrutarás de la vida musical. Explorá, amplificá tu creatividad y desarrollá tu pasión.",
        "stock": 7,
        "discount": "0%",
        "type": "Electrica",
        "left-hand": false,
        "Additional-information": "Importante: Cuando clickeas en “comprar” asumis el compromiso de compra. Por lo tanto te recomendamos que antes: 1. Estés seguro de querer adquirir el artículo., 2. Consultes el saldo disponible de tu tarjeta de crédito, 3."
    }
    ,
    {
        "id": "32",
        "brand": "Femmto",
        "model": "AG003",
        "fullName": ["Fonseca", "65 Medio Concierto"],
        "img": [
            "https://http2.mlstatic.com/D_NQ_NP_794399-MLA51258924308_082022-O.webp",
            "https://http2.mlstatic.com/D_NQ_NP_683434-MLA51258901443_082022-O.webp"
        ],
        "color": [ "naranja, azul"],
        "price": 18700.00,
        "strings": 6,
        "description": "Disfrutá con esta guitarra Femmto de la conexión con la música. Está diseñada para aficionados y profesionales. Con este instrumento descubrirás nuevos acordes, entonarás tus canciones y disfrutarás de la vida musical.",
        "stock": 15,
        "discount": "15%",
        "type": "Electroacústica",
        "left-hand": false,
        "Additional-information": "Importante: Cuando clickeas en “comprar” asumis el compromiso de compra. Por lo tanto te recomendamos que antes: 1. Estés seguro de querer adquirir el artículo., 2. Consultes el saldo disponible de tu tarjeta de crédito, 3."
    }
    ,
    {
        "id": "33",
        "brand": "Sigma",
        "model": "DME",
        "fullName": ["Fonseca", "65 Medio Concierto"],
        "img": [
            "https://http2.mlstatic.com/D_NQ_NP_673794-MLA46517661576_062021-O.webp"
        ],
           
        "color": [
            "natural"
        ],
        "price": 86355.30,
        "strings": 6,
        "description": "Sigma es algo más que una marca de guitarras. Desde 1970, acompaña el sueño de un sinfín de personas en el arte de componer sonidos. Su calidad y adaptabilidad la vuelven ideal para ser utilizada en todo momento.",
        "stock": 15,
        "discount": "0%",
        "type": "Electroacústica",
        "left-hand": true,
        "Additional-information": "Las IMÁGENES en la presente publicación usualmente son provistas por los proveedores por lo que son a modo ilustrativo y pueden ser modificadas por los fabricantes/importadores sin previo aviso."
    }
    ,
    {
        "id": "34",
        "brand": "Fender",
        "model": "CC-60SCE",
        "fullName": ["Fonseca", "65 Medio Concierto"],
        "img": [
            "https://http2.mlstatic.com/D_NQ_NP_792046-MLA40694915541_022020-O.webp",
            "https://http2.mlstatic.com/D_NQ_NP_940268-MLA40694915557_022020-O.webp"
        ],
           
        "color": ["negro, natural"],
        "price": 170958.90,
        "strings": 6,
        "description": "Guitarras prácticas y funcionales, para aficionados y profesionales. Fender es una empresa que transforma la música en todo el mundo y atraviesa una gran variedad de géneros. Es el mayor fabricante internacional y sus productos representan un ícono cultural.",
        "stock": 26,
        "discount": "5%",
        "type": "Electroacústica",
        "left-hand": true,
        "Additional-information": "Las IMÁGENES en la presente publicación usualmente son provistas por los proveedores por lo que son a modo ilustrativo y pueden ser modificadas por los fabricantes/importadores sin previo aviso."
    }
    ,
    {
        "id": "35",
        "brand": "Sunset",
        "model": "Fk60",
        "fullName": ["Fonseca", "65 Medio Concierto"],
        "img": [
            "https://http2.mlstatic.com/D_NQ_NP_2X_984494-MLA51467397870_092022-F.webp"
        ],
           
        "color": [
            "natural"
        ],
        "price": 32978.90,
        "strings": 6,
        "description": "Guitarra Electroacústica Sunset Fk60 con Corte y EQ2BANDAS, Sunset Fk-60 es una guitarra electroacústica , con cuerdas de acero , construida en madera de alta calidad, viene con Ecualizador de 2 bandas con un piezo eléctrico integrado en la guitarra con salida plug 6.5 mm.",
        "stock": 14,
        "discount": "0%",
        "type": "Electroacústica",
        "left-hand": false,
        "Additional-information": "Realizamos envíos gratis en el día en CABA Y GBA comprando antes de las 12 hs con flete propio."
    }
    ,
    {
        "id": "36",
        "brand": "Sunset",
        "model": "FK 1000",
        "fullName": ["Fonseca", "65 Medio Concierto"],
        "img": [
            "https://http2.mlstatic.com/D_NQ_NP_802570-MLA50626696362_072022-O.webp"
        ],
           
        "color": [
            "caoba"
        ],
        "price": 54893.90,
        "strings": 6,
        "description": "Guitarra electroacústica Sunset FK 1000, Esta excelente guitarra de cuerdas acero ofrece una tapa en caoba de gran tono y calidad en su sonido .Su pre amplificador ecualizador de 5 bandas con display LCD + afinador ofrece un control total en graves , agudos , medios1,medios2 y presencia .",
        "stock": 14,
        "discount": "10%",
        "type": "Electroacústica",
        "left-hand": true,
        "Additional-information": "Somos una tienda de instrumentos musicales conformada por técnicos y músicos para darte la mejor atención y servicio."
    }
    ,
    {
        "id": "37",
        "brand": "Fender",
        "model": "California",
        "fullName": ["Fonseca", "65 Medio Concierto"],
        "img": [
            "https://http2.mlstatic.com/D_NQ_NP_908479-MLA43814183461_102020-O.webp",
            "https://http2.mlstatic.com/D_NQ_NP_625779-MLA43814681210_102020-O.webp"
        ],
           
        "color": ["roja, negro"],
        "price": 203616.60,
        "strings": 6,
        "description": "Guitarras prácticas y funcionales, para aficionados y profesionales. Fender es una empresa que transforma la música en todo el mundo y atraviesa una gran variedad de géneros. Es el mayor fabricante internacional y sus productos representan un ícono cultural.",
        "stock": 8,
        "discount": "0%",
        "type": "Electroacústica",
        "left-hand": false,
        "Additional-information": "Somos una tienda de instrumentos musicales conformada por técnicos y músicos para darte la mejor atención y servicio."
    }
    ,
    {
        "id": "38",
        "brand": "Fender",
        "model": "California Malibu",
        "fullName": ["Fonseca", "65 Medio Concierto"],
        "img": [
            "https://http2.mlstatic.com/D_NQ_NP_742206-MLA43405656060_092020-O.webp"
        ],
           
        "color": [
            "blanco"
        ],
        "price": 205608.60,
        "strings": 6,
        "description": "Calidad que se hace notar, Las cuerdas de metal se caracterizan por su bajo estiramiento y resistencia a la corrosión y abrasión. Son más duraderas, sólidas y generan un sonido brillante y claro.",
        "stock": 8,
        "discount": "0%",
        "type": "Electroacústica",
        "left-hand": true,
        "Additional-information": "Somos una tienda de instrumentos musicales conformada por técnicos y músicos para darte la mejor atención y servicio."
    },

    {
        "id": "39",
        "brand": "Gracia",
        "model": "G10 EQ",
        "fullName": ["Fonseca", "65 Medio Concierto"],
        "img": [
            "https://http2.mlstatic.com/D_NQ_NP_947031-MLA45098678257_032021-O.webp"
        ],
           
        "color": [
            "natural"
        ],
        "price": 48744.04,
        "strings": 6,
        "description": "Nuevo Modelo!!!!! La linea de guitarras G10 cuenta con una serie de caracteristicas unicas de este modelo como su cuerpo de CAOBA con Corte, trastes de ALPACA, Refuerzo de pala en NOGAL y 2 pines para colgar correa tradicional.",
        "stock": 18,
        "discount": "0%",
        "type": "Electrocriolla",
        "left-hand": true,
        "Additional-information": "Somos una tienda de instrumentos musicales conformada por técnicos y músicos para darte la mejor atención y servicio."
    }

    ,

    {
        "id": "40",
        "brand": "Romulo Garcia",
        "model": "CG100EQ",
        "fullName": ["Fonseca", "65 Medio Concierto"],
        "img": [
            "https://http2.mlstatic.com/D_NQ_NP_767517-MLA49170780655_022022-O.webp",
            "https://http2.mlstatic.com/D_NQ_NP_688876-MLA51633923214_092022-O.webp"
        ],
           
        "color": ["naranja, negro"],
        "price": 16566.50,
        "strings": 6,
        "description": "Guitarra electrocriolla romulo garcia cg100eq + funda + puas + - tamaño adulto - ecualizador 2 bandas tono/volume",
        "stock": 18,
        "discount": "0%",
        "type": "Electrocriolla",
        "left-hand": false,
        "Additional-information": "Garantia 6 meses, envios sin cargo a todo el pais"
    }
    ,

    {
        "id": "41",
        "brand": "Fonseca",
        "model": "40",
        "fullName": ["Fonseca", "65 Medio Concierto"],
        "img": [
            "https://http2.mlstatic.com/D_NQ_NP_2X_963458-MLA45713153323_042021-F.webp"
        ],
           
        "color": [
            "natural"
        ],
        "price": 113315.40,
        "strings": 6,
        "description": "Guitarra de Estudio con Corte ( Cutaway).vCaracterísticasvTapa: Pino Abeto LaminadovAros: Caoba o Nogal MacizovFondo: Caoba o Nogal LaminadovOrnamentos: Doble Filete NegrovCorte: SivMástil: CedrovDiapasón",
        "stock": 8,
        "discount": "7%",
        "type": "Electrocriolla",
        "left-hand": false,
        "Additional-information": "Garantia 6 meses, envios sin cargo a todo el pais"
    },
    {
        "id": "42",
        "brand": "Superior",
        "model": "c47",
        "fullName": ["Fonseca", "65 Medio Concierto"],
        "img": [
            "https://http2.mlstatic.com/D_NQ_NP_658410-MLA44627532925_012021-O.webp",
            "https://http2.mlstatic.com/D_NQ_NP_889018-MLA44627570236_012021-O.webp"
        ],
           
        "color": ["azul, negro"],
        "price": 14719.20,
        "strings": 6,
        "description": "Tamaño adulto estándar 4/4 39, Construida en madera genuina, Trastes en bronce, Acabado en laca brillante, Encordado completo calidad superior",
        "stock": 30,
        "discount": "0%",
        "type": "Electrocriolla",
        "left-hand": true,
        "Additional-information": "Cualquier duda o consulta estamos a tu disposición, Gracias por visitar esta publicación"
    }
    ,
    {
        "id": "43",
        "brand": "Cort",
        "model": "Cec 3",
        "fullName": ["Fonseca", "65 Medio Concierto"],
        "img": [
            "https://http2.mlstatic.com/D_NQ_NP_650333-MLA31589260343_072019-O.webp"
        ],
           
        "color": [
            "natural"
        ],
        "price": 103232.20,
        "strings": 6,
        "description": "Tamaño adulto estándar 4/4 39, Construida en madera genuina, Trastes en bronce, Acabado en laca brillante, Encordado completo calidad superior",
        "stock": 30,
        "discount": "0%",
        "type": "Electrocriolla",
        "left-hand": true,
        "Additional-information": "Cualquier duda o consulta estamos a tu disposición, Gracias por visitar esta publicación"
    }
    ,
    {
        "id": "44",
        "brand": "Romulo Garcia",
        "model": "Cg100eq",
        "fullName": ["Fonseca", "65 Medio Concierto"],
        "img": [
            "https://http2.mlstatic.com/D_NQ_NP_793602-MLA51633757028_092022-O.webp",
            "https://http2.mlstatic.com/D_NQ_NP_706330-MLA49171193348_022022-O.webp"
        ],
           
        "color": [
            "natural, negro"
        ],
        "price": 19490.00,
        "strings": 6,
        "description": "Guitarra electrocriolla romulo garcia cg100eq + funda + cable + puas + tamaño adulto - ecualizador 2 bandas tono/volume",
        "stock": 8,
        "discount": "5%",
        "type": "Electrocriolla",
        "left-hand": false,
        "Additional-information": "Cualquier duda o consulta estamos a tu disposición, Gracias por visitar esta publicación"
    }
    ,
    {
        "id": "45",
        "brand": "Gracia",
        "model": "Gold C",
        "fullName": ["Fonseca", "65 Medio Concierto"],
        "img": [
            "https://http2.mlstatic.com/D_NQ_NP_652218-MLA49719109564_042022-O.webp"
            
        ],
           
        "color": [
            "dorada"
        ],
        "price": 67449.00,
        "strings": 6,
        "description": "Guitarra electrocriolla romulo garcia cg100eq + funda + cable + puas + tamaño adulto - ecualizador 2 bandas tono/volume",
        "stock": 28,
        "discount": "5%",
        "type": "Electrocriolla",
        "left-hand": true,
        "Additional-information": "Cualquier duda o consulta estamos a tu disposición, Gracias por visitar esta publicación"
    }
    ,
    {
        "id": "46",
        "brand": "Estudio ",
        "model": "Niños",
        "fullName": ["Fonseca", "65 Medio Concierto"],
        "img": [
            "https://http2.mlstatic.com/D_NQ_NP_875287-MLA43018506594_082020-O.webp",
            "https://http2.mlstatic.com/D_NQ_NP_965336-MLA43018506590_082020-O.webp",
            "https://http2.mlstatic.com/D_NQ_NP_754355-MLA43020208838_082020-O.webp"
            
        ],
           
        "color": [
            "caoba, natural"
        ],
        "price": 44593.15,
        "strings": 6,
        "description": "La Serie Valencia 100 nos ofrece una guitarra de cuerda de nylon con todas las características para estudiar y tocar el instrumento.",
        "stock": 28,
        "discount": "15%",
        "type": "Electrocriolla",
        "left-hand": false,
        "Additional-information": "Cualquier duda o consulta estamos a tu disposición, Gracias por visitar esta publicación"
    }
    ,
    {
        "id": "47",
        "brand": "Cort",
        "model": "AF510",
        "fullName": ["Fonseca", "65 Medio Concierto"],
        "img": [
           "https://http2.mlstatic.com/D_NQ_NP_839258-MLA43784419538_102020-O.webp",
           "https://http2.mlstatic.com/D_NQ_NP_983077-MLA43784374543_102020-O.webp"            
        ],
           
        "color": ["caoba, natural"],
        "price": 52249.15,
        "strings": 6,
        "description": "Calidad que se hace notar, Las cuerdas de metal se caracterizan por su bajo estiramiento y resistencia a la corrosión y abrasión.",
        "stock": 8,
        "discount": "0%",
        "type": "Electroacústica",
        "left-hand": false,
        "Additional-information": "Cualquier duda o consulta estamos a tu disposición, Gracias por visitar esta publicación"
    }
    ,
    {
        "id": "48",
        "brand": "Parquer",
        "model": "AC209TBBLEQ4",
        "fullName": ["Fonseca", "65 Medio Concierto"],
        "img": [
           "https://http2.mlstatic.com/D_NQ_NP_752332-MLA41220506983_032020-O.webp",
           "https://http2.mlstatic.com/D_NQ_NP_603761-MLA41221061473_032020-O.webp"            
        ],
           
        "color": [
            "azul"
        ],
        "price": 62887.50,
        "strings": 6,
        "description": "La tapa de tilo tiene un peso y una densidad que te ofrecen un sonido con más cuerpo. Esta madera presenta un buen equilibrio de graves, por lo que suena con más peso rítmico y un tono suave.",
        "stock": 16,
        "discount": "0%",
        "type": "Electroacústica",
        "left-hand": false,
        "Additional-information": "Cualquier duda o consulta estamos a tu disposición, Gracias por visitar esta publicación"
    }
    ,
    {
        "id": "49",
        "brand": "Yamaha",
        "model": "FX370C",
        "fullName": ["Fonseca", "65 Medio Concierto"],
        "img": [
           "https://http2.mlstatic.com/D_NQ_NP_999887-MLA43823811094_102020-O.webp",
           "https://http2.mlstatic.com/D_NQ_NP_969478-MLA43823811016_102020-O.webp"            
        ],
           
        "color": ["negro, dorada"],
        "price": 62887.50,
        "strings": 6,
        "description": "Calidad que se hace notar, Las cuerdas de metal se caracterizan por su bajo estiramiento y resistencia a la corrosión y abrasión. Son más duraderas, sólidas y generan un sonido brillante y claro.",
        "stock": 6,
        "discount": "10%",
        "type": "Electroacústica",
        "left-hand": true,
        "Additional-information": "Cualquier duda o consulta estamos a tu disposición, Gracias por visitar esta publicación"
    }
    ,
    {
        "id": "50",
        "brand": "Gracia",
        "model": "Caoba",
        "fullName": ["Fonseca", "65 Medio Concierto"],
        "img": [
           "https://http2.mlstatic.com/D_NQ_NP_918127-MLA46518329963_062021-O.webp",
           "https://http2.mlstatic.com/D_NQ_NP_764062-MLA46518406499_062021-O.webp"            
        ],
           
        "color": [
            "caoba"
        ],
        "price": 69687.59,
        "strings": 6,
        "description": "Con un toque artesanal único plasmado en sus materiales, Gracia acompaña a la historia musical desde el año 1870. Sus guitarras poseen alcance internacional y son utilizadas tantos por principiantes como por grandes referentes de la música.",
        "stock": 26,
        "discount": "18%",
        "type": "Electrocriolla",
        "left-hand": false,
        "Additional-information": "Cualquier duda o consulta estamos a tu disposición, Gracias por visitar esta publicación"
    }








    




    



    



    


]